insequence/__init__.py
insequence/_action.py
insequence/api.py
insequence/chain.py
insequence/checks.py
insequence/py.typed
insequence-2.dist-info/METADATA
insequence-2.dist-info/WHEEL
insequence-2.dist-info/top_level.txt
insequence-2.dist-info/RECORD
