Metadata-Version: 2.1
Name: insequence
Version: 2
Summary: A python library for function composition and execution orchestration.
Author: Christian Heinze
Project-URL: Repository, https://codeberg.org/christianheinze/insequence
Classifier: Development Status :: 4 - Beta
Classifier: Intended Audience :: Developers
Classifier: License :: OSI Approved :: Apache Software License
Classifier: Operating System :: OS Independent
Classifier: Programming Language :: Python :: 3 :: Only
Classifier: Programming Language :: Python :: 3.10
Classifier: Programming Language :: Python :: 3.11
Classifier: Programming Language :: Python :: 3.12
Classifier: Typing :: Typed
Requires-Python: >=3.10
Provides-Extra: test
Requires-Dist: coverage ; extra == 'test'
Requires-Dist: nox ; extra == 'test'
Requires-Dist: pytest ; extra == 'test'
Requires-Dist: pytest-cov ; extra == 'test'
Requires-Dist: pytest-randomly ; extra == 'test'
Requires-Dist: tomli ; (python_version < "3.11") and extra == 'test'
Provides-Extra: typing
Requires-Dist: typing-extensions >=4.1 ; extra == 'typing'
